braket/strawberryfields_plugin/__init__.py
braket/strawberryfields_plugin/_version.py
braket/strawberryfields_plugin/braket_engine.py
braket/strawberryfields_plugin/braket_job.py
amazon_braket_strawberryfields_plugin-1.1.0.post1.dist-info/LICENSE
amazon_braket_strawberryfields_plugin-1.1.0.post1.dist-info/METADATA
amazon_braket_strawberryfields_plugin-1.1.0.post1.dist-info/NOTICE
amazon_braket_strawberryfields_plugin-1.1.0.post1.dist-info/WHEEL
amazon_braket_strawberryfields_plugin-1.1.0.post1.dist-info/top_level.txt
amazon_braket_strawberryfields_plugin-1.1.0.post1.dist-info/RECORD
