Metadata-Version: 2.1
Name: amazon-braket-strawberryfields-plugin
Version: 1.1.0.post1
Summary: An open source framework for using Amazon Braket devices with the Strawberry Fields photonic device programming library
Home-page: https://github.com/aws/amazon-braket-strawberryfields-plugin-python
Author: Amazon Web Services
License: Apache License 2.0
Keywords: Amazon AWS Quantum
Classifier: Development Status :: 5 - Production/Stable
Classifier: Intended Audience :: Developers
Classifier: Natural Language :: English
Classifier: License :: OSI Approved :: Apache Software License
Classifier: Programming Language :: Python
Classifier: Programming Language :: Python :: 3.8
Classifier: Programming Language :: Python :: 3.9
Classifier: Programming Language :: Python :: 3.10
Requires-Python: >= 3.8.2
License-File: LICENSE
License-File: NOTICE
Requires-Dist: amazon-braket-sdk (>=1.25.0)
Requires-Dist: strawberryfields (>=0.23.0)
Provides-Extra: test
Requires-Dist: black ; extra == 'test'
Requires-Dist: docutils (<0.16,>=0.10) ; extra == 'test'
Requires-Dist: flake8 ; extra == 'test'
Requires-Dist: isort ; extra == 'test'
Requires-Dist: pre-commit ; extra == 'test'
Requires-Dist: pylint ; extra == 'test'
Requires-Dist: pytest ; extra == 'test'
Requires-Dist: pytest-cov ; extra == 'test'
Requires-Dist: pytest-mock ; extra == 'test'
Requires-Dist: pytest-rerunfailures ; extra == 'test'
Requires-Dist: pytest-xdist ; extra == 'test'
Requires-Dist: sphinx ; extra == 'test'
Requires-Dist: sphinx-automodapi ; extra == 'test'
Requires-Dist: sphinx-rtd-theme ; extra == 'test'
Requires-Dist: sphinxcontrib-apidoc ; extra == 'test'
Requires-Dist: tox ; extra == 'test'
